fitsio/__init__.py
fitsio/_fitsio_wrap.cpython-314t-x86_64-linux-musl.so
fitsio/_version.py
fitsio/fits_exceptions.py
fitsio/fitsio_pywrap.c
fitsio/fitslib.py
fitsio/header.py
fitsio/util.py
fitsio/hdu/__init__.py
fitsio/hdu/base.py
fitsio/hdu/image.py
fitsio/hdu/table.py
fitsio/test_images/test_gzip_compressed_image.fits.fz
fitsio/tests/__init__.py
fitsio/tests/checks.py
fitsio/tests/makedata.py
fitsio/tests/test_empty_slice.py
fitsio/tests/test_header.py
fitsio/tests/test_header_junk.py
fitsio/tests/test_image.py
fitsio/tests/test_image_compression.py
fitsio/tests/test_image_compression_defaults.py
fitsio/tests/test_lib.py
fitsio/tests/test_table.py
fitsio/tests/test_util.py
fitsio/tests/test_warnings.py
fitsio.libs/libbz2-b428631a.so.1.0.8
fitsio-1.3.0.dist-info/METADATA
fitsio-1.3.0.dist-info/WHEEL
fitsio-1.3.0.dist-info/top_level.txt
fitsio-1.3.0.dist-info/RECORD
fitsio-1.3.0.dist-info/licenses/LICENSE.txt
