Metadata-Version: 2.4
Name: fitsio
Version: 1.3.0
Summary: A full featured python library to read from and write to FITS files.
Home-page: https://github.com/esheldon/fitsio
Author: Erin Scott Sheldon
Author-email: erin.sheldon@gmail.com
License: GPL
Classifier: Development Status :: 5 - Production/Stable
Classifier: License :: OSI Approved :: GNU General Public License (GPL)
Classifier: Topic :: Scientific/Engineering :: Astronomy
Classifier: Intended Audience :: Science/Research
Requires-Python: >=3.8
License-File: LICENSE.txt
Requires-Dist: numpy>=1.7
Dynamic: author
Dynamic: author-email
Dynamic: classifier
Dynamic: description
Dynamic: description-content-type
Dynamic: home-page
Dynamic: license
Dynamic: license-file
Dynamic: requires-dist
Dynamic: requires-python
Dynamic: summary
